.gitignore
README.rst
buildout.cfg
setup.cfg
setup.py
collective/__init__.py
collective.socialpublisher.egg-info/PKG-INFO
collective.socialpublisher.egg-info/SOURCES.txt
collective.socialpublisher.egg-info/dependency_links.txt
collective.socialpublisher.egg-info/entry_points.txt
collective.socialpublisher.egg-info/namespace_packages.txt
collective.socialpublisher.egg-info/not-zip-safe
collective.socialpublisher.egg-info/requires.txt
collective.socialpublisher.egg-info/top_level.txt
collective/socialpublisher/TODO.txt
collective/socialpublisher/__init__.py
collective/socialpublisher/adapters.py
collective/socialpublisher/config.py
collective/socialpublisher/configure.zcml
collective/socialpublisher/interfaces.py
collective/socialpublisher/testing.py
collective/socialpublisher/utility.py
collective/socialpublisher/utils.py
collective/socialpublisher/browser/__init__.py
collective/socialpublisher/browser/configure.zcml
collective/socialpublisher/browser/controlpanel.py
collective/socialpublisher/browser/viewlet_social.pt
collective/socialpublisher/browser/viewlets.py
collective/socialpublisher/browser/views.py
collective/socialpublisher/browser/resources/socialpublisher.css
collective/socialpublisher/browser/resources/socialpublisher.js
collective/socialpublisher/locales/collective.socialpublisher.pot
collective/socialpublisher/locales/en/LC_MESSAGES/collective.socialpublisher.po
collective/socialpublisher/locales/it/LC_MESSAGES/collective.socialpublisher.po
collective/socialpublisher/profiles/default/controlpanel.xml
collective/socialpublisher/profiles/default/cssregistry.xml
collective/socialpublisher/profiles/default/jsregistry.xml
collective/socialpublisher/profiles/default/metadata.xml
collective/socialpublisher/profiles/default/registry.xml
collective/socialpublisher/tests/MANAGER.txt
collective/socialpublisher/tests/__init__.py
collective/socialpublisher/tests/test_doctest.py
collective/socialpublisher/tests/test_misc.py
collective/socialpublisher/tests/utils.py
docs/CREDITS.txt
docs/HISTORY.txt
docs/INSTALL.txt
docs/LICENSE.GPL
docs/LICENSE.txt