Metadata-Version: 1.0
Name: collective.socialpublisher
Version: 1.0a3
Summary: Manage and automate social publishing on Plone sites
Home-page: https://github.com/simahawk/collective.socialpublisher
Author: Simone Orsi [simahawk]
Author-email: simahawk@gmail.com
License: GPL
Platform: UNKNOWN
Classifier: Development Status :: 3 - Alpha
Classifier: Framework :: Plone
Classifier: Framework :: Plone :: 4.2
Classifier: Programming Language :: Python
